DisnanaLG/DisnanaLG.py
DisnanaLG/__init__.py
DisnanaLG-1.0.7.dist-info/METADATA
DisnanaLG-1.0.7.dist-info/WHEEL
DisnanaLG-1.0.7.dist-info/top_level.txt
DisnanaLG-1.0.7.dist-info/RECORD
