Metadata-Version: 2.1
Name: DisnanaLG
Version: 1.0.7
Summary: seaborn-analyzer: data visualization of regression, classification and distribution
Author: Disnana
Author-email: support@disnana.com
Maintainer: Disnana
Maintainer-email: support@disnana.com
License: BSD 3-Clause
Classifier: Intended Audience :: Science/Research
Classifier: License :: OSI Approved :: BSD License
Classifier: Programming Language :: Python :: 3
Classifier: Programming Language :: Python :: 3.6
Classifier: Programming Language :: Python :: 3.7
Classifier: Programming Language :: Python :: 3.8
Classifier: Programming Language :: Python :: 3.9
Classifier: Programming Language :: Python :: 3 :: Only
Requires-Python: >=3.6
